envvar/__init__.py
envvar/load.py
envvar/version.py
py_envvar-0.0.1.dist-info/LICENSE
py_envvar-0.0.1.dist-info/METADATA
py_envvar-0.0.1.dist-info/WHEEL
py_envvar-0.0.1.dist-info/top_level.txt
py_envvar-0.0.1.dist-info/RECORD
