Metadata-Version: 2.1
Name: py-envvar
Version: 0.0.1
Summary: Easiest way to deal with env vars
Home-page: https://github.com/drish/envvar
Author: Derich Pacheco
Author-email: carlosderich@gmail.com
License: UNKNOWN
Keywords: env,environment variables
Platform: UNKNOWN
Classifier: Development Status :: 3 - Alpha
Classifier: Intended Audience :: Developers
Classifier: License :: OSI Approved :: MIT License
Classifier: Natural Language :: English
Classifier: Operating System :: OS Independent
Classifier: Programming Language :: Python :: 3
Classifier: Programming Language :: Python :: 3.7
Classifier: Programming Language :: Python :: 3.8
Requires-Python: >3.7.0
Requires-Dist: pyyaml (>="6.0")
